dace/__init__.py
dace/builtin_hooks.py
dace/config.py
dace/config_schema.yml
dace/data.py
dace/distr_types.py
dace/dtypes.py
dace/fpga_testing.py
dace/hooks.py
dace/jupyter.py
dace/library.py
dace/memlet.py
dace/properties.py
dace/registry.py
dace/serialize.py
dace/sourcemap.py
dace/subsets.py
dace/symbolic.py
dace/version.py
dace/cli/__init__.py
dace/cli/dacelab.py
dace/cli/daceprof.py
dace/cli/fcdc.py
dace/cli/progress.py
dace/cli/sdfgcc.py
dace/cli/sdfv.py
dace/codegen/CMakeLists.txt
dace/codegen/__init__.py
dace/codegen/codegen.py
dace/codegen/codeobject.py
dace/codegen/common.py
dace/codegen/compiled_sdfg.py
dace/codegen/compiler.py
dace/codegen/control_flow.py
dace/codegen/cppunparse.py
dace/codegen/dispatcher.py
dace/codegen/exceptions.py
dace/codegen/prettycode.py
dace/codegen/instrumentation/__init__.py
dace/codegen/instrumentation/fpga.py
dace/codegen/instrumentation/gpu_events.py
dace/codegen/instrumentation/likwid.py
dace/codegen/instrumentation/papi.py
dace/codegen/instrumentation/provider.py
dace/codegen/instrumentation/report.py
dace/codegen/instrumentation/timer.py
dace/codegen/instrumentation/data/__init__.py
dace/codegen/instrumentation/data/data_dump.py
dace/codegen/instrumentation/data/data_report.py
dace/codegen/targets/__init__.py
dace/codegen/targets/cpp.py
dace/codegen/targets/cpu.py
dace/codegen/targets/cuda.py
dace/codegen/targets/fpga.py
dace/codegen/targets/framecode.py
dace/codegen/targets/intel_fpga.py
dace/codegen/targets/mpi.py
dace/codegen/targets/rtl.py
dace/codegen/targets/snitch.py
dace/codegen/targets/target.py
dace/codegen/targets/unroller.py
dace/codegen/targets/xilinx.py
dace/codegen/targets/mlir/__init__.py
dace/codegen/targets/mlir/mlir.cmake
dace/codegen/targets/mlir/mlir.py
dace/codegen/targets/mlir/utils.py
dace/codegen/targets/sve/__init__.py
dace/codegen/targets/sve/codegen.py
dace/codegen/targets/sve/infer.py
dace/codegen/targets/sve/preprocess.py
dace/codegen/targets/sve/type_compatibility.py
dace-0.16.1.dist-info/AUTHORS
dace-0.16.1.dist-info/LICENSE
dace-0.16.1.dist-info/METADATA
dace-0.16.1.dist-info/WHEEL
dace-0.16.1.dist-info/entry_points.txt
dace-0.16.1.dist-info/top_level.txt
dace-0.16.1.dist-info/RECORD
