Metadata-Version: 2.1
Name: dace
Version: 0.16.1
Summary: Data-Centric Parallel Programming Framework
Home-page: https://github.com/spcl/dace
Author: SPCL @ ETH Zurich
Author-email: talbn@inf.ethz.ch
Classifier: Programming Language :: Python :: 3
Classifier: License :: OSI Approved :: BSD License
Classifier: Operating System :: OS Independent
Requires-Python: >=3.6, <3.13
License-File: LICENSE
License-File: AUTHORS
Requires-Dist: numpy <2.0
Requires-Dist: networkx >=2.5
Requires-Dist: astunparse
Requires-Dist: sympy >=1.9
Requires-Dist: pyyaml
Requires-Dist: ply
Requires-Dist: websockets
Requires-Dist: jinja2
Requires-Dist: fparser >=0.1.3
Requires-Dist: aenum >=3.1
Requires-Dist: dill
Requires-Dist: pyreadline ; platform_system == "Windows"
Requires-Dist: dataclasses ; python_version < "3.7"
Requires-Dist: typing-compat ; python_version < "3.8"
Provides-Extra: docs
Requires-Dist: jinja2 <3.2.0 ; extra == 'docs'
Requires-Dist: sphinx-autodoc-typehints ; extra == 'docs'
Requires-Dist: sphinx-rtd-theme >=0.5.1 ; extra == 'docs'
Provides-Extra: testing
Requires-Dist: coverage ; extra == 'testing'
Requires-Dist: pytest-cov ; extra == 'testing'
Requires-Dist: scipy ; extra == 'testing'
Requires-Dist: absl-py ; extra == 'testing'
Requires-Dist: opt-einsum ; extra == 'testing'
Requires-Dist: pymlir ; extra == 'testing'
Requires-Dist: click ; extra == 'testing'
